[{"team": "Timberwolves", "timestamp": "2026-05-06T01:59:28.461317", "sentiment": 50, "mentions": 0}, {"team": "Wild", "timestamp": "2026-05-06T01:59:29.091425", "sentiment": 50, "mentions": 0}, {"team": "Timberwolves", "timestamp": "2026-05-06T03:45:31.980519", "sentiment": 50, "mentions": 0}, {"team": "Wild", "timestamp": "2026-05-06T03:45:32.594628", "sentiment": 50, "mentions": 0}, {"team": "Timberwolves", "timestamp": "2026-05-06T06:31:18.113979", "sentiment": 50, "mentions": 0}, {"team": "Wild", "timestamp": "2026-05-06T06:31:18.681377", "sentiment": 50, "mentions": 0}, {"team": "Timberwolves", "timestamp": "2026-05-06T09:24:36.640348", "sentiment": 50, "mentions": 0}, {"team": "Wild", "timestamp": "2026-05-06T09:24:37.310190", "sentiment": 50, "mentions": 0}]